gadfastetdc/__init__.py
gadfastetdc-0.0.1.dist-info/LICENSE
gadfastetdc-0.0.1.dist-info/METADATA
gadfastetdc-0.0.1.dist-info/WHEEL
gadfastetdc-0.0.1.dist-info/top_level.txt
gadfastetdc-0.0.1.dist-info/RECORD
