Metadata-Version: 2.1
Name: gadfastetdc
Version: 0.0.1
Summary: A FastAPI integration with Etcd for managing configuration settings via a RESTful API
Home-page: https://github.com/AlexDemure/gadfastetdc
Author: Alexander Grishchenko
Author-email: alexanderdemure@gmail.com
Classifier: Programming Language :: Python :: 3
Classifier: License :: OSI Approved :: MIT License
Classifier: Operating System :: OS Independent
Requires-Python: >=3.8
License-File: LICENSE
Requires-Dist: etcd3
Requires-Dist: fastapi
